modbus_tcp_server/__init__.py
modbus_tcp_server/bits.py
modbus_tcp_server/datagrams.py
modbus_tcp_server/exceptions.py
modbus_tcp_server/processor.py
modbus_tcp_server/run.py
modbus_tcp_server/data_source/__init__.py
modbus_tcp_server/data_source/base.py
modbus_tcp_server/data_source/testing.py
modbus_tcp_server/network/__init__.py
modbus_tcp_server/network/accept_thread.py
modbus_tcp_server/network/conn_thread.py
modbus_tcp_server-0.6.dist-info/LICENSE
modbus_tcp_server-0.6.dist-info/METADATA
modbus_tcp_server-0.6.dist-info/WHEEL
modbus_tcp_server-0.6.dist-info/entry_points.txt
modbus_tcp_server-0.6.dist-info/top_level.txt
modbus_tcp_server-0.6.dist-info/zip-safe
modbus_tcp_server-0.6.dist-info/RECORD
