Metadata-Version: 2.1
Name: modbus-tcp-server
Version: 0.6
Summary: A Python3 MODBUS TCP server for testing purposes
Home-page: https://github.com/smok-serwis/modbus-tcp-server
Author: Piotr Maślanka
Author-email: pmaslanka@smok.co
License: UNKNOWN
Project-URL: Code, https://github.com/smok-serwis/modbus-tcp-server
Project-URL: Issue tracker, https://github.com/smok-serwis/modbus-tcp-server/issues
Keywords: modbus,server,tcp,scada
Platform: UNKNOWN
Classifier: Programming Language :: Python
Classifier: Programming Language :: Python :: 3.6
Classifier: Programming Language :: Python :: 3.7
Classifier: Programming Language :: Python :: 3.8
Classifier: Programming Language :: Python :: 3.9
Classifier: Programming Language :: Python :: Implementation :: CPython
Classifier: Programming Language :: Python :: Implementation :: PyPy
Classifier: Operating System :: OS Independent
Classifier: Development Status :: 4 - Beta
Classifier: License :: OSI Approved :: MIT License
Classifier: Topic :: Software Development :: Libraries
Classifier: Topic :: System :: Networking
Classifier: Topic :: Communications
Requires-Python: !=2.7.*,!=3.0.*,!=3.1.*,!=3.2.*,!=3.3.*,!=3.4.*,!=3.5.*
Requires-Dist: satella
